lexitron/__init__.py
lexitron/agid-common.txt
lexitron/agid-proper.txt
lexitron/lexitron.py
Lexitron-2.1.2.dist-info/LICENSE
Lexitron-2.1.2.dist-info/METADATA
Lexitron-2.1.2.dist-info/WHEEL
Lexitron-2.1.2.dist-info/entry_points.txt
Lexitron-2.1.2.dist-info/top_level.txt
Lexitron-2.1.2.dist-info/RECORD
