Metadata-Version: 2.2
Name: Lexitron
Version: 2.1.2
Summary: A command-line regex search engine for the English language
Author: Rothos
License: GNU GPL Version 2
Project-URL: Homepage, http://github.com/rothos/lexitron
Keywords: english,dictionary,crossword,spelling,words,lexicon,search
Classifier: Programming Language :: Python :: 3
Requires-Python: >=3.7
License-File: LICENSE
Requires-Dist: importlib-metadata; python_version < "3.8"
Requires-Dist: importlib-resources; python_version < "3.8"
